LICENSE.txt
MANIFEST.in
README.md
setup.cfg
setup.py
requirements/requirements-all.txt
requirements/requirements-dev.txt
requirements/requirements-test.txt
veracitools/__init__.py
veracitools/_version.py
veracitools/expect_context.py
veracitools.egg-info/PKG-INFO
veracitools.egg-info/SOURCES.txt
veracitools.egg-info/dependency_links.txt
veracitools.egg-info/top_level.txt