Metadata-Version: 2.1
Name: veracitools
Version: 0.1.4
Summary: Testing utilities
Home-page: https://github.com/pepkit/veracitools/
Author: Vince Reuter
License: BSD2
Keywords: utility,utilities,tools
Platform: UNKNOWN
Classifier: Development Status :: 4 - Beta
Classifier: License :: OSI Approved :: BSD License
Classifier: Programming Language :: Python :: 2.7
Classifier: Programming Language :: Python :: 3.5
Classifier: Programming Language :: Python :: 3.6
License-File: LICENSE.txt
